verifikio/__init__.py
verifikio/async_client.py
verifikio/client.py
verifikio/client_original.py
verifikio/exceptions.py
verifikio/integrations/__init__.py
verifikio/integrations/crewai.py
verifikio/integrations/langchain.py
verifikio_sdk-1.2.0.dist-info/licenses/LICENSE
verifikio_sdk-1.2.0.dist-info/METADATA
verifikio_sdk-1.2.0.dist-info/WHEEL
verifikio_sdk-1.2.0.dist-info/top_level.txt
verifikio_sdk-1.2.0.dist-info/RECORD
