Metadata-Version: 2.4
Name: verifikio-sdk
Version: 1.2.0
Summary: Official Python SDK for Verifik.io trust infrastructure platform
Home-page: https://github.com/verifik-io/verifikio-python
Author: Verifik.io
Author-email: "Verifik.io" <support@verifik.io>
Maintainer-email: "Verifik.io" <support@verifik.io>
License-Expression: MIT
Project-URL: Homepage, https://verifik.io
Project-URL: Documentation, https://docs.verifik.io/sdk/python
Project-URL: Repository, https://github.com/verifik-io/verifikio-python
Project-URL: Bug Tracker, https://github.com/verifik-io/verifikio-python/issues
Project-URL: API Reference, https://docs.verifik.io/api
Keywords: audit,logging,security,ai,agents,blockchain,verification,trust,infrastructure
Classifier: Development Status :: 5 - Production/Stable
Classifier: Intended Audience :: Developers
Classifier: Topic :: Software Development :: Libraries :: Python Modules
Classifier: Topic :: System :: Logging
Classifier: Topic :: Security
Classifier: Programming Language :: Python :: 3
Classifier: Programming Language :: Python :: 3.7
Classifier: Programming Language :: Python :: 3.8
Classifier: Programming Language :: Python :: 3.9
Classifier: Programming Language :: Python :: 3.10
Classifier: Programming Language :: Python :: 3.11
Classifier: Programming Language :: Python :: 3.12
Classifier: Operating System :: OS Independent
Requires-Python: >=3.7
License-File: LICENSE
Requires-Dist: build>=0.10.0
Requires-Dist: requests>=2.25.0
Requires-Dist: setuptools>=68.0.0
Requires-Dist: twine>=4.0.2
Provides-Extra: dev
Requires-Dist: pytest>=6.0; extra == "dev"
Requires-Dist: pytest-cov>=2.0; extra == "dev"
Requires-Dist: black>=21.0; extra == "dev"
Requires-Dist: flake8>=3.8; extra == "dev"
Requires-Dist: mypy>=0.812; extra == "dev"
Provides-Extra: async
Requires-Dist: aiohttp>=3.8.0; extra == "async"
Provides-Extra: crewai
Requires-Dist: crewai>=0.1.0; extra == "crewai"
Provides-Extra: langchain
Requires-Dist: langchain>=0.0.200; extra == "langchain"
Provides-Extra: all
Requires-Dist: aiohttp>=3.8.0; extra == "all"
Requires-Dist: crewai>=0.1.0; extra == "all"
Requires-Dist: langchain>=0.0.200; extra == "all"
Dynamic: author
Dynamic: home-page
Dynamic: license-file
Dynamic: requires-python
